[{"index": 0, "publishingCountryCode": "AR", "publishingCountry": "Argentina", "Total Occurrences": 4, "Unique Sharks (with ID)": 4, "Top 3 Countries Visited": "Mexico", "Avg Per Year (all)": 1.33, "Avg Per Year (after 2020)": 1.0, "Avg Per Year (2010 - 2020)": 1.5, "Avg Per Year (2000 - 2010)": 0.0, "Avg Per Year (before 2000)": 0.0, "Jan": 0, "Feb": 0, "Mar": 0, "Apr": 0, "May": 0, "Jun": 0, "Jul": 4, "Aug": 0, "Sep": 0, "Oct": 0, "Nov": 0, "Dec": 0, "HUMAN_OBSERVATION": 4, "MACHINE_OBSERVATION": 0, "Oldest Occurrence": "2016-07-23", "Newest Occurrence": "2022-07-06", "occurrences (year)": "1 (2016), 2 (2020), 1 (2022)"}, {"index": 1, "publishingCountryCode": "AU", "publishingCountry": "Australia", "Total Occurrences": 1253, "Unique Sharks (with ID)": 199, "Top 3 Countries Visited": "Australia > Indonesia > Philippines", "Avg Per Year (all)": 48.19, "Avg Per Year (after 2020)": 19.83, "Avg Per Year (2010 - 2020)": 100.82, "Avg Per Year (2000 - 2010)": 3.0, "Avg Per Year (before 2000)": 3.0, "Jan": 42, "Feb": 28, "Mar": 81, "Apr": 88, "May": 97, "Jun": 108, "Jul": 171, "Aug": 38, "Sep": 115, "Oct": 115, "Nov": 99, "Dec": 26, "HUMAN_OBSERVATION": 332, "MACHINE_OBSERVATION": 745, "Oldest Occurrence": "1964-04", "Newest Occurrence": "2026-01-03", "occurrences (year)": "2 (1964), 1 (1965), 1 (1993), 8 (1995), 1 (2000), 1 (2003), 1 (2005), 4 (2008), 6 (2009), 5 (2010), 193 (2011), 44 (2012), 267 (2013), 97 (2014), 54 (2015), 133 (2016), 240 (2017), 32 (2018), 25 (2019), 19 (2020), 42 (2021), 38 (2022), 12 (2023), 14 (2024), 12 (2025), 1 (2026)"}, {"index": 2, "publishingCountryCode": "BE", "publishingCountry": "Belgium", "Total Occurrences": 4, "Unique Sharks (with ID)": 0, "Top 3 Countries Visited": "Spain > Mexico", "Avg Per Year (all)": 1.0, "Avg Per Year (after 2020)": 1.0, "Avg Per Year (2010 - 2020)": 1.0, "Avg Per Year (2000 - 2010)": 1.0, "Avg Per Year (before 2000)": 0.0, "Jan": 0, "Feb": 0, "Mar": 1, "Apr": 1, "May": 0, "Jun": 0, "Jul": 0, "Aug": 0, "Sep": 1, "Oct": 0, "Nov": 1, "Dec": 0, "HUMAN_OBSERVATION": 3, "MACHINE_OBSERVATION": 1, "Oldest Occurrence": "2003-03-31", "Newest Occurrence": "2023-04-25", "occurrences (year)": "1 (2003), 1 (2015), 1 (2017), 1 (2023)"}, {"index": 3, "publishingCountryCode": "BJ", "publishingCountry": "Benin", "Total Occurrences": 5, "Unique Sharks (with ID)": 0, "Top 3 Countries Visited": "Benin", "Avg Per Year (all)": 1.0, "Avg Per Year (after 2020)": 0.0, "Avg Per Year (2010 - 2020)": 0.0, "Avg Per Year (2000 - 2010)": 1.0, "Avg Per Year (before 2000)": 0.0, "Jan": 0, "Feb": 0, "Mar": 0, "Apr": 0, "May": 1, "Jun": 1, "Jul": 2, "Aug": 1, "Sep": 0, "Oct": 0, "Nov": 0, "Dec": 0, "HUMAN_OBSERVATION": 5, "MACHINE_OBSERVATION": 0, "Oldest Occurrence": "2000-07-09", "Newest Occurrence": "2009-05-24", "occurrences (year)": "1 (2000), 1 (2002), 1 (2005), 1 (2007), 1 (2009)"}, {"index": 4, "publishingCountryCode": "BR", "publishingCountry": "Brazil", "Total Occurrences": 1, "Unique Sharks (with ID)": 0, "Top 3 Countries Visited": "Brazil", "Avg Per Year (all)": 1.0, "Avg Per Year (after 2020)": 0.0, "Avg Per Year (2010 - 2020)": 0.0, "Avg Per Year (2000 - 2010)": 1.0, "Avg Per Year (before 2000)": 0.0, "Jan": 0, "Feb": 0, "Mar": 0, "Apr": 0, "May": 0, "Jun": 0, "Jul": 0, "Aug": 1, "Sep": 0, "Oct": 0, "Nov": 0, "Dec": 0, "HUMAN_OBSERVATION": 1, "MACHINE_OBSERVATION": 0, "Oldest Occurrence": "2002-08-01", "Newest Occurrence": "2002-08-01", "occurrences (year)": "1 (2002)"}, {"index": 5, "publishingCountryCode": "CA", "publishingCountry": "Canada", "Total Occurrences": 22, "Unique Sharks (with ID)": 21, "Top 3 Countries Visited": "Mexico > Philippines > Australia", "Avg Per Year (all)": 1.69, "Avg Per Year (after 2020)": 2.2, "Avg Per Year (2010 - 2020)": 1.5, "Avg Per Year (2000 - 2010)": 1.0, "Avg Per Year (before 2000)": 1.0, "Jan": 1, "Feb": 7, "Mar": 3, "Apr": 2, "May": 0, "Jun": 1, "Jul": 3, "Aug": 2, "Sep": 0, "Oct": 0, "Nov": 1, "Dec": 2, "HUMAN_OBSERVATION": 21, "MACHINE_OBSERVATION": 0, "Oldest Occurrence": "1995-07-15", "Newest Occurrence": "2025-03-29", "occurrences (year)": "1 (1995), 1 (2009), 1 (2010), 1 (2011), 1 (2012), 1 (2014), 1 (2018), 4 (2019), 1 (2021), 1 (2022), 4 (2023), 4 (2024), 1 (2025)"}, {"index": 6, "publishingCountryCode": "CL", "publishingCountry": "Chile", "Total Occurrences": 1, "Unique Sharks (with ID)": 1, "Top 3 Countries Visited": "Mexico", "Avg Per Year (all)": 1.0, "Avg Per Year (after 2020)": 0.0, "Avg Per Year (2010 - 2020)": 1.0, "Avg Per Year (2000 - 2010)": 0.0, "Avg Per Year (before 2000)": 0.0, "Jan": 0, "Feb": 0, "Mar": 0, "Apr": 0, "May": 0, "Jun": 0, "Jul": 0, "Aug": 0, "Sep": 0, "Oct": 0, "Nov": 1, "Dec": 0, "HUMAN_OBSERVATION": 1, "MACHINE_OBSERVATION": 0, "Oldest Occurrence": "2018-11-10", "Newest Occurrence": "2018-11-10", "occurrences (year)": "1 (2018)"}, {"index": 7, "publishingCountryCode": "CO", "publishingCountry": "Colombia", "Total Occurrences": 19, "Unique Sharks (with ID)": 5, "Top 3 Countries Visited": "Colombia > Honduras > Mexico", "Avg Per Year (all)": 2.71, "Avg Per Year (after 2020)": 2.0, "Avg Per Year (2010 - 2020)": 4.0, "Avg Per Year (2000 - 2010)": 1.0, "Avg Per Year (before 2000)": 0.0, "Jan": 0, "Feb": 0, "Mar": 1, "Apr": 1, "May": 3, "Jun": 1, "Jul": 7, "Aug": 2, "Sep": 1, "Oct": 0, "Nov": 1, "Dec": 0, "HUMAN_OBSERVATION": 19, "MACHINE_OBSERVATION": 0, "Oldest Occurrence": "2006-11-14", "Newest Occurrence": "2024", "occurrences (year)": "1 (2006), 1 (2010), 6 (2018), 5 (2019), 2 (2021), 2 (2022), 2 (2024)"}, {"index": 8, "publishingCountryCode": "CR", "publishingCountry": "Costa Rica", "Total Occurrences": 2, "Unique Sharks (with ID)": 2, "Top 3 Countries Visited": "Costa Rica", "Avg Per Year (all)": 1.0, "Avg Per Year (after 2020)": 0.0, "Avg Per Year (2010 - 2020)": 1.0, "Avg Per Year (2000 - 2010)": 0.0, "Avg Per Year (before 2000)": 0.0, "Jan": 0, "Feb": 0, "Mar": 0, "Apr": 0, "May": 0, "Jun": 1, "Jul": 1, "Aug": 0, "Sep": 0, "Oct": 0, "Nov": 0, "Dec": 0, "HUMAN_OBSERVATION": 2, "MACHINE_OBSERVATION": 0, "Oldest Occurrence": "2016-06-14", "Newest Occurrence": "2019-07-11", "occurrences (year)": "1 (2016), 1 (2019)"}, {"index": 10, "publishingCountryCode": "EC", "publishingCountry": "Ecuador", "Total Occurrences": 2818, "Unique Sharks (with ID)": 61, "Top 3 Countries Visited": "Ecuador > Peru > Costa Rica", "Avg Per Year (all)": 281.8, "Avg Per Year (after 2020)": 1.0, "Avg Per Year (2010 - 2020)": 402.14, "Avg Per Year (2000 - 2010)": 0.0, "Avg Per Year (before 2000)": 0.0, "Jan": 293, "Feb": 76, "Mar": 16, "Apr": 1, "May": 2, "Jun": 0, "Jul": 242, "Aug": 297, "Sep": 601, "Oct": 587, "Nov": 412, "Dec": 291, "HUMAN_OBSERVATION": 5, "MACHINE_OBSERVATION": 2813, "Oldest Occurrence": "2011-07-14", "Newest Occurrence": "2025-05-26", "occurrences (year)": "20 (2011), 19 (2012), 54 (2013), 241 (2014), 1137 (2015), 1222 (2016), 122 (2017), 1 (2021), 1 (2023), 1 (2025)"}, {"index": 12, "publishingCountryCode": "FI", "publishingCountry": "Finland", "Total Occurrences": 1, "Unique Sharks (with ID)": 1, "Top 3 Countries Visited": "Maldives", "Avg Per Year (all)": 1.0, "Avg Per Year (after 2020)": 1.0, "Avg Per Year (2010 - 2020)": 0.0, "Avg Per Year (2000 - 2010)": 0.0, "Avg Per Year (before 2000)": 0.0, "Jan": 1, "Feb": 0, "Mar": 0, "Apr": 0, "May": 0, "Jun": 0, "Jul": 0, "Aug": 0, "Sep": 0, "Oct": 0, "Nov": 0, "Dec": 0, "HUMAN_OBSERVATION": 1, "MACHINE_OBSERVATION": 0, "Oldest Occurrence": "2022-01-18", "Newest Occurrence": "2022-01-18", "occurrences (year)": "1 (2022)"}, {"index": 13, "publishingCountryCode": "FR", "publishingCountry": "France", "Total Occurrences": 143, "Unique Sharks (with ID)": 0, "Top 3 Countries Visited": "Thailand > Philippines > Maldives", "Avg Per Year (all)": 6.09, "Avg Per Year (after 2020)": 5.0, "Avg Per Year (2010 - 2020)": 9.64, "Avg Per Year (2000 - 2010)": 3.29, "Avg Per Year (before 2000)": 1.25, "Jan": 7, "Feb": 10, "Mar": 16, "Apr": 13, "May": 13, "Jun": 11, "Jul": 9, "Aug": 9, "Sep": 11, "Oct": 18, "Nov": 15, "Dec": 5, "HUMAN_OBSERVATION": 141, "MACHINE_OBSERVATION": 0, "Oldest Occurrence": "1989-11-29", "Newest Occurrence": "2022-11-13", "occurrences (year)": "1 (1989), 2 (1996), 1 (1997), 1 (1998), 3 (2004), 3 (2005), 2 (2006), 5 (2007), 4 (2008), 2 (2009), 4 (2010), 1 (2011), 29 (2012), 16 (2013), 14 (2014), 15 (2015), 7 (2016), 9 (2017), 8 (2018), 2 (2019), 1 (2020), 3 (2021), 7 (2022)"}, {"index": 9, "publishingCountryCode": "DE", "publishingCountry": "Germany", "Total Occurrences": 11, "Unique Sharks (with ID)": 0, "Top 3 Countries Visited": "Australia > Malaysia > Mexico", "Avg Per Year (all)": 1.57, "Avg Per Year (after 2020)": 1.0, "Avg Per Year (2010 - 2020)": 2.0, "Avg Per Year (2000 - 2010)": 1.5, "Avg Per Year (before 2000)": 1.0, "Jan": 2, "Feb": 0, "Mar": 4, "Apr": 1, "May": 0, "Jun": 0, "Jul": 0, "Aug": 1, "Sep": 0, "Oct": 1, "Nov": 0, "Dec": 2, "HUMAN_OBSERVATION": 11, "MACHINE_OBSERVATION": 0, "Oldest Occurrence": "1995-01-20", "Newest Occurrence": "2022-10-10", "occurrences (year)": "1 (1995), 1 (2002), 2 (2010), 3 (2013), 2 (2015), 1 (2016), 1 (2022)"}, {"index": 15, "publishingCountryCode": "GT", "publishingCountry": "Guatemala", "Total Occurrences": 1, "Unique Sharks (with ID)": 0, "Top 3 Countries Visited": "Guatemala", "Avg Per Year (all)": 1.0, "Avg Per Year (after 2020)": 1.0, "Avg Per Year (2010 - 2020)": 0.0, "Avg Per Year (2000 - 2010)": 0.0, "Avg Per Year (before 2000)": 0.0, "Jan": 0, "Feb": 1, "Mar": 0, "Apr": 0, "May": 0, "Jun": 0, "Jul": 0, "Aug": 0, "Sep": 0, "Oct": 0, "Nov": 0, "Dec": 0, "HUMAN_OBSERVATION": 1, "MACHINE_OBSERVATION": 0, "Oldest Occurrence": "2021-02-19", "Newest Occurrence": "2021-02-19", "occurrences (year)": "1 (2021)"}, {"index": 17, "publishingCountryCode": "IN", "publishingCountry": "India", "Total Occurrences": 1, "Unique Sharks (with ID)": 1, "Top 3 Countries Visited": "India", "Avg Per Year (all)": 1.0, "Avg Per Year (after 2020)": 0.0, "Avg Per Year (2010 - 2020)": 0.0, "Avg Per Year (2000 - 2010)": 1.0, "Avg Per Year (before 2000)": 0.0, "Jan": 0, "Feb": 1, "Mar": 0, "Apr": 0, "May": 0, "Jun": 0, "Jul": 0, "Aug": 0, "Sep": 0, "Oct": 0, "Nov": 0, "Dec": 0, "HUMAN_OBSERVATION": 1, "MACHINE_OBSERVATION": 0, "Oldest Occurrence": "2009-02-22", "Newest Occurrence": "2009-02-22", "occurrences (year)": "1 (2009)"}, {"index": 16, "publishingCountryCode": "IL", "publishingCountry": "Israel", "Total Occurrences": 16, "Unique Sharks (with ID)": 3, "Top 3 Countries Visited": "Israel > Madagascar > Tanzania", "Avg Per Year (all)": 2.29, "Avg Per Year (after 2020)": 2.0, "Avg Per Year (2010 - 2020)": 3.0, "Avg Per Year (2000 - 2010)": 0.0, "Avg Per Year (before 2000)": 0.0, "Jan": 0, "Feb": 0, "Mar": 1, "Apr": 1, "May": 2, "Jun": 0, "Jul": 2, "Aug": 1, "Sep": 2, "Oct": 6, "Nov": 0, "Dec": 1, "HUMAN_OBSERVATION": 16, "MACHINE_OBSERVATION": 0, "Oldest Occurrence": "2019-04-26", "Newest Occurrence": "2025-10-13", "occurrences (year)": "2 (2019), 4 (2020), 1 (2021), 2 (2022), 2 (2023), 2 (2024), 3 (2025)"}, {"index": 18, "publishingCountryCode": "JP", "publishingCountry": "Japan", "Total Occurrences": 7, "Unique Sharks (with ID)": 0, "Top 3 Countries Visited": "Japan > Australia > Philippines", "Avg Per Year (all)": 1.0, "Avg Per Year (after 2020)": 0.0, "Avg Per Year (2010 - 2020)": 1.0, "Avg Per Year (2000 - 2010)": 1.0, "Avg Per Year (before 2000)": 1.0, "Jan": 0, "Feb": 1, "Mar": 0, "Apr": 0, "May": 3, "Jun": 0, "Jul": 2, "Aug": 1, "Sep": 0, "Oct": 0, "Nov": 0, "Dec": 0, "HUMAN_OBSERVATION": 7, "MACHINE_OBSERVATION": 0, "Oldest Occurrence": "1995-07-27", "Newest Occurrence": "2016-05-04", "occurrences (year)": "1 (1995), 1 (1996), 1 (2004), 1 (2005), 1 (2010), 1 (2011), 1 (2016)"}, {"index": 19, "publishingCountryCode": "MX", "publishingCountry": "Mexico", "Total Occurrences": 200, "Unique Sharks (with ID)": 200, "Top 3 Countries Visited": "Mexico > St. Helena > Honduras", "Avg Per Year (all)": 9.52, "Avg Per Year (after 2020)": 13.2, "Avg Per Year (2010 - 2020)": 12.4, "Avg Per Year (2000 - 2010)": 1.8, "Avg Per Year (before 2000)": 1.0, "Jan": 26, "Feb": 9, "Mar": 18, "Apr": 20, "May": 5, "Jun": 14, "Jul": 25, "Aug": 34, "Sep": 15, "Oct": 14, "Nov": 11, "Dec": 9, "HUMAN_OBSERVATION": 199, "MACHINE_OBSERVATION": 0, "Oldest Occurrence": "1989-04-05", "Newest Occurrence": "2025-11-21", "occurrences (year)": "1 (1989), 1 (2000), 1 (2005), 1 (2007), 1 (2008), 5 (2009), 7 (2011), 3 (2012), 1 (2013), 3 (2014), 18 (2015), 20 (2016), 24 (2017), 18 (2018), 24 (2019), 6 (2020), 4 (2021), 19 (2022), 21 (2023), 15 (2024), 7 (2025)"}, {"index": 20, "publishingCountryCode": "NL", "publishingCountry": "Netherlands", "Total Occurrences": 60, "Unique Sharks (with ID)": 0, "Top 3 Countries Visited": "St. Helena > Mexico > Maldives", "Avg Per Year (all)": 3.75, "Avg Per Year (after 2020)": 3.0, "Avg Per Year (2010 - 2020)": 5.0, "Avg Per Year (2000 - 2010)": 1.67, "Avg Per Year (before 2000)": 1.0, "Jan": 0, "Feb": 4, "Mar": 1, "Apr": 28, "May": 1, "Jun": 2, "Jul": 8, "Aug": 10, "Sep": 0, "Oct": 1, "Nov": 4, "Dec": 1, "HUMAN_OBSERVATION": 60, "MACHINE_OBSERVATION": 0, "Oldest Occurrence": "1994-06-21", "Newest Occurrence": "2025-08-19", "occurrences (year)": "1 (1994), 3 (2008), 1 (2009), 1 (2010), 1 (2011), 1 (2012), 2 (2013), 1 (2016), 4 (2017), 25 (2018), 5 (2019), 3 (2021), 2 (2022), 3 (2023), 2 (2024), 5 (2025)"}, {"index": 21, "publishingCountryCode": "NZ", "publishingCountry": "New Zealand", "Total Occurrences": 14, "Unique Sharks (with ID)": 14, "Top 3 Countries Visited": "New Zealand > Australia > Ecuador", "Avg Per Year (all)": 1.27, "Avg Per Year (after 2020)": 1.75, "Avg Per Year (2010 - 2020)": 1.0, "Avg Per Year (2000 - 2010)": 1.0, "Avg Per Year (before 2000)": 0.0, "Jan": 1, "Feb": 2, "Mar": 0, "Apr": 2, "May": 2, "Jun": 0, "Jul": 1, "Aug": 1, "Sep": 2, "Oct": 2, "Nov": 1, "Dec": 0, "HUMAN_OBSERVATION": 14, "MACHINE_OBSERVATION": 0, "Oldest Occurrence": "2007-02-11", "Newest Occurrence": "2025-10-26", "occurrences (year)": "1 (2007), 1 (2009), 1 (2011), 1 (2013), 1 (2014), 1 (2016), 1 (2019), 1 (2021), 1 (2023), 3 (2024), 2 (2025)"}, {"index": 22, "publishingCountryCode": "PA", "publishingCountry": "Panama", "Total Occurrences": 3, "Unique Sharks (with ID)": 3, "Top 3 Countries Visited": "Panama > Costa Rica", "Avg Per Year (all)": 1.0, "Avg Per Year (after 2020)": 1.0, "Avg Per Year (2010 - 2020)": 1.0, "Avg Per Year (2000 - 2010)": 0.0, "Avg Per Year (before 2000)": 0.0, "Jan": 1, "Feb": 0, "Mar": 0, "Apr": 0, "May": 0, "Jun": 0, "Jul": 0, "Aug": 0, "Sep": 0, "Oct": 0, "Nov": 1, "Dec": 1, "HUMAN_OBSERVATION": 3, "MACHINE_OBSERVATION": 0, "Oldest Occurrence": "2018-12-04", "Newest Occurrence": "2022-11-27", "occurrences (year)": "1 (2018), 1 (2020), 1 (2022)"}, {"index": 23, "publishingCountryCode": "PT", "publishingCountry": "Portugal", "Total Occurrences": 11, "Unique Sharks (with ID)": 6, "Top 3 Countries Visited": "Portugal > Maldives > Mozambique", "Avg Per Year (all)": 1.38, "Avg Per Year (after 2020)": 1.0, "Avg Per Year (2010 - 2020)": 1.0, "Avg Per Year (2000 - 2010)": 2.5, "Avg Per Year (before 2000)": 0.0, "Jan": 0, "Feb": 1, "Mar": 0, "Apr": 0, "May": 0, "Jun": 0, "Jul": 2, "Aug": 3, "Sep": 1, "Oct": 3, "Nov": 0, "Dec": 1, "HUMAN_OBSERVATION": 11, "MACHINE_OBSERVATION": 0, "Oldest Occurrence": "2008-07-13", "Newest Occurrence": "2025-02-16", "occurrences (year)": "4 (2008), 1 (2010), 1 (2017), 1 (2019), 1 (2020), 1 (2021), 1 (2022), 1 (2025)"}, {"index": 28, "publishingCountryCode": "ZA", "publishingCountry": "South Africa", "Total Occurrences": 10, "Unique Sharks (with ID)": 4, "Top 3 Countries Visited": "South Africa > Mozambique", "Avg Per Year (all)": 1.67, "Avg Per Year (after 2020)": 0.0, "Avg Per Year (2010 - 2020)": 1.75, "Avg Per Year (2000 - 2010)": 0.0, "Avg Per Year (before 2000)": 1.5, "Jan": 4, "Feb": 0, "Mar": 1, "Apr": 0, "May": 0, "Jun": 1, "Jul": 1, "Aug": 0, "Sep": 0, "Oct": 1, "Nov": 0, "Dec": 2, "HUMAN_OBSERVATION": 8, "MACHINE_OBSERVATION": 0, "Oldest Occurrence": "1973-01", "Newest Occurrence": "2017-03-11", "occurrences (year)": "1 (1973), 2 (1974), 2 (2011), 2 (2014), 2 (2015), 1 (2017)"}, {"index": 11, "publishingCountryCode": "ES", "publishingCountry": "Spain", "Total Occurrences": 18, "Unique Sharks (with ID)": 17, "Top 3 Countries Visited": "Mexico > Mozambique > Maldives", "Avg Per Year (all)": 1.64, "Avg Per Year (after 2020)": 1.33, "Avg Per Year (2010 - 2020)": 2.0, "Avg Per Year (2000 - 2010)": 1.0, "Avg Per Year (before 2000)": 1.0, "Jan": 1, "Feb": 3, "Mar": 0, "Apr": 0, "May": 0, "Jun": 0, "Jul": 5, "Aug": 0, "Sep": 0, "Oct": 6, "Nov": 2, "Dec": 1, "HUMAN_OBSERVATION": 17, "MACHINE_OBSERVATION": 0, "Oldest Occurrence": "1931-01-01", "Newest Occurrence": "2025-11-09", "occurrences (year)": "1 (1931), 1 (2009), 1 (2013), 1 (2015), 2 (2016), 6 (2018), 1 (2019), 1 (2020), 2 (2021), 1 (2024), 1 (2025)"}, {"index": 24, "publishingCountryCode": "SE", "publishingCountry": "Sweden", "Total Occurrences": 13, "Unique Sharks (with ID)": 1, "Top 3 Countries Visited": "Brazil > China > Mexico", "Avg Per Year (all)": 1.08, "Avg Per Year (after 2020)": 0.0, "Avg Per Year (2010 - 2020)": 1.0, "Avg Per Year (2000 - 2010)": 0.0, "Avg Per Year (before 2000)": 1.09, "Jan": 0, "Feb": 2, "Mar": 1, "Apr": 2, "May": 1, "Jun": 1, "Jul": 2, "Aug": 1, "Sep": 0, "Oct": 1, "Nov": 0, "Dec": 2, "HUMAN_OBSERVATION": 1, "MACHINE_OBSERVATION": 0, "Oldest Occurrence": "1931-12-31", "Newest Occurrence": "2020-02-16", "occurrences (year)": "1 (1931), 1 (1970), 1 (1971), 1 (1976), 1 (1982), 1 (1983), 2 (1984), 1 (1985), 1 (1992), 1 (1993), 1 (1995), 1 (2020)"}, {"index": 25, "publishingCountryCode": "TW", "publishingCountry": "Taiwan", "Total Occurrences": 9, "Unique Sharks (with ID)": 7, "Top 3 Countries Visited": "Taiwan > Philippines > Christmas Island", "Avg Per Year (all)": 1.29, "Avg Per Year (after 2020)": 1.67, "Avg Per Year (2010 - 2020)": 1.0, "Avg Per Year (2000 - 2010)": 0.0, "Avg Per Year (before 2000)": 1.0, "Jan": 0, "Feb": 0, "Mar": 0, "Apr": 0, "May": 2, "Jun": 2, "Jul": 1, "Aug": 1, "Sep": 0, "Oct": 1, "Nov": 1, "Dec": 1, "HUMAN_OBSERVATION": 7, "MACHINE_OBSERVATION": 0, "Oldest Occurrence": "1956-10-25", "Newest Occurrence": "2025-05-02", "occurrences (year)": "1 (1956), 1 (1995), 1 (2016), 1 (2019), 2 (2023), 2 (2024), 1 (2025)"}, {"index": 14, "publishingCountryCode": "GB", "publishingCountry": "United Kingdom", "Total Occurrences": 171, "Unique Sharks (with ID)": 24, "Top 3 Countries Visited": "Qatar > Japan > Australia", "Avg Per Year (all)": 7.12, "Avg Per Year (after 2020)": 4.67, "Avg Per Year (2010 - 2020)": 13.7, "Avg Per Year (2000 - 2010)": 6.67, "Avg Per Year (before 2000)": 1.67, "Jan": 3, "Feb": 6, "Mar": 3, "Apr": 6, "May": 17, "Jun": 16, "Jul": 30, "Aug": 18, "Sep": 11, "Oct": 4, "Nov": 2, "Dec": 8, "HUMAN_OBSERVATION": 24, "MACHINE_OBSERVATION": 0, "Oldest Occurrence": "1993-05-05", "Newest Occurrence": "2024-12-29", "occurrences (year)": "2 (1993), 2 (1997), 1 (1999), 2 (2000), 4 (2001), 1 (2002), 1 (2004), 1 (2005), 1 (2006), 1 (2007), 4 (2009), 45 (2010), 16 (2011), 18 (2012), 19 (2013), 22 (2014), 5 (2015), 1 (2016), 4 (2017), 4 (2019), 3 (2020), 3 (2022), 4 (2023), 7 (2024)"}, {"index": 26, "publishingCountryCode": "US", "publishingCountry": "United States", "Total Occurrences": 1846, "Unique Sharks (with ID)": 1066, "Top 3 Countries Visited": "Mexico > Australia > United States", "Avg Per Year (all)": 32.21, "Avg Per Year (after 2020)": 84.67, "Avg Per Year (2010 - 2020)": 80.64, "Avg Per Year (2000 - 2010)": 18.91, "Avg Per Year (before 2000)": 1.35, "Jan": 142, "Feb": 79, "Mar": 89, "Apr": 86, "May": 71, "Jun": 121, "Jul": 166, "Aug": 192, "Sep": 114, "Oct": 131, "Nov": 110, "Dec": 106, "HUMAN_OBSERVATION": 1142, "MACHINE_OBSERVATION": 680, "Oldest Occurrence": "0000 00 00", "Newest Occurrence": "Mar1980", "occurrences (year)": "1 (1858), 1 (1902), 1 (1936), 1 (1937), 1 (1951), 2 (1953), 1 (1965), 1 (1970), 1 (1971), 1 (1975), 1 (1976), 1 (1983), 1 (1984), 1 (1992), 1 (1993), 3 (1994), 2 (1995), 4 (1996), 1 (1997), 1 (1998), 3 (2000), 3 (2001), 1 (2002), 2 (2003), 1 (2004), 6 (2005), 4 (2006), 12 (2007), 11 (2008), 49 (2009), 116 (2010), 73 (2011), 36 (2012), 61 (2013), 62 (2014), 74 (2015), 89 (2016), 94 (2017), 143 (2018), 87 (2019), 52 (2020), 41 (2021), 58 (2022), 118 (2023), 145 (2024), 143 (2025), 3 (2026)"}, {"index": 29, "publishingCountryCode": "ZZ", "publishingCountry": "Unknown", "Total Occurrences": 17, "Unique Sharks (with ID)": 0, "Top 3 Countries Visited": "South Africa > India > Mexico", "Avg Per Year (all)": 1.31, "Avg Per Year (after 2020)": 1.0, "Avg Per Year (2010 - 2020)": 1.17, "Avg Per Year (2000 - 2010)": 1.67, "Avg Per Year (before 2000)": 1.0, "Jan": 4, "Feb": 3, "Mar": 1, "Apr": 3, "May": 1, "Jun": 0, "Jul": 2, "Aug": 0, "Sep": 0, "Oct": 1, "Nov": 1, "Dec": 1, "HUMAN_OBSERVATION": 0, "MACHINE_OBSERVATION": 0, "Oldest Occurrence": "1997-02-24", "Newest Occurrence": "2024-11-25", "occurrences (year)": "1 (1997), 2 (2000), 1 (2001), 1 (2002), 1 (2007), 3 (2009), 2 (2010), 1 (2012), 1 (2013), 1 (2017), 1 (2018), 1 (2020), 1 (2024)"}, {"index": 27, "publishingCountryCode": "VE", "publishingCountry": "Venezuela", "Total Occurrences": 11, "Unique Sharks (with ID)": 0, "Top 3 Countries Visited": "Ecuador", "Avg Per Year (all)": 1.57, "Avg Per Year (after 2020)": 1.5, "Avg Per Year (2010 - 2020)": 1.0, "Avg Per Year (2000 - 2010)": 1.75, "Avg Per Year (before 2000)": 0.0, "Jan": 0, "Feb": 0, "Mar": 1, "Apr": 1, "May": 1, "Jun": 1, "Jul": 0, "Aug": 3, "Sep": 1, "Oct": 3, "Nov": 0, "Dec": 0, "HUMAN_OBSERVATION": 11, "MACHINE_OBSERVATION": 0, "Oldest Occurrence": "2002-04-04", "Newest Occurrence": "2022-10-08", "occurrences (year)": "4 (2002), 1 (2004), 1 (2005), 1 (2010), 1 (2018), 2 (2021), 1 (2022)"}]